<?xml version="1.0" encoding="UTF-8"?>
<odoo>
	<data>
        <!-- model_network_provider Layout form view -->
        <record id="network_provider_layout_form" model="ir.ui.view">
            <field name="name">Network Provider Layout</field>
            <field name="model">model_network_provider</field>
            <field name="arch" type="xml">
                <form string="Network Provider Layout">
                    <sheet>
                        <group>
                            <group>
                                <field name="accredited_network__c"/>
                                <field name="create_uid"/>
                                <field name="Name"/>
                            </group>
                            <group>
                                <field name="How_c"/>
                                <field name="write_uid" string='Last Modified By'/>
                            </group>
                        </group>
                    </sheet>
                </form>
            </field>
        </record>

        <!-- model_network_provider tree view -->
        <record id="network_provider_layout_tree" model="ir.ui.view">
            <field name="name">Network Provider Layout Tree</field>
            <field name="model">model_network_provider</field>
            <field name="arch" type="xml">
                <tree>
                    <field name="Name" />
                    <field name="OwnerId"/>
                    <field name="create_uid" />
                    <field name="write_uid"/>
                </tree>
            </field>
        </record>

        <!-- model_network_provider action window -->
        <record id="network_provider_layout_action" model="ir.actions.act_window">
            <field name="name">Network Provider Layout</field>
            <field name="type">ir.actions.act_window</field>
            <field name="res_model">model_network_provider</field>
            <field name="view_mode">tree,form</field>
            <field name="view_ids" eval="[(5, 0, 0), 
                (0, 0, {'view_mode': 'tree', 'view_id': ref('network_provider_layout_tree')}),
                (0, 0, {'view_mode': 'form', 'view_id': ref('network_provider_layout_form')})]"/>
            <field name="help" type="html">
                <p class="o_view_nocontent_smiling_face">
                    No records available.
                </p>
            </field>
        </record>
    </data>
</odoo>